onyxengine/__init__.py
onyxengine/api.py
onyxengine/api_utils.py
onyxengine/data/__init__.py
onyxengine/data/dataset.py
onyxengine/modeling/__init__.py
onyxengine/modeling/model_base_config.py
onyxengine/modeling/model_features.py
onyxengine/modeling/model_from_config.py
onyxengine/modeling/model_simulator.py
onyxengine/modeling/model_training.py
onyxengine/modeling/validate_hyperparam.py
onyxengine/modeling/lr_schedulers/__init__.py
onyxengine/modeling/lr_schedulers/cosine_annealing_warm_restarts.py
onyxengine/modeling/lr_schedulers/cosine_decay_with_warmup.py
onyxengine/modeling/models/__init__.py
onyxengine/modeling/models/mlp.py
onyxengine/modeling/models/rnn.py
onyxengine/modeling/models/transformer.py
onyxengine/modeling/optimizers/__init__.py
onyxengine/modeling/optimizers/adamw.py
onyxengine/modeling/optimizers/sgd.py
onyxengine-0.1.11.dist-info/licenses/LICENSE
onyxengine-0.1.11.dist-info/METADATA
onyxengine-0.1.11.dist-info/WHEEL
onyxengine-0.1.11.dist-info/top_level.txt
onyxengine-0.1.11.dist-info/RECORD
