Metadata-Version: 2.4
Name: onyxengine
Version: 0.1.11
Summary: The official Python library for the Onyx Engine.
Author-email: Onyx <support@onyx-robotics.com>
License:                                  Apache License
Project-URL: Homepage, https://github.com/onyx-robotics/onyx-engine
Classifier: Programming Language :: Python :: 3
Classifier: License :: OSI Approved :: Apache Software License
Classifier: Operating System :: OS Independent
License-File: LICENSE
Requires-Dist: requests-toolbelt==1.0.0
Requires-Dist: websockets<15,>=13
Requires-Dist: pandas
Requires-Dist: pydantic
Requires-Dist: tqdm
Requires-Dist: torch
Dynamic: license-file
